lxmlh/__init__.py
lxmlh/config.py
lxmlh/helpers.py
lxmlh/parsers.py
lxmlh-1.3.3.dist-info/LICENSE
lxmlh-1.3.3.dist-info/METADATA
lxmlh-1.3.3.dist-info/WHEEL
lxmlh-1.3.3.dist-info/top_level.txt
lxmlh-1.3.3.dist-info/RECORD
