Metadata-Version: 2.1
Name: lxmlh
Version: 1.3.3
Summary: lxml helper Python package 
Author-email: Mina Sami <sami.mg@outlook.com>
Maintainer-email: Mina Sami <sami.mg@outlook.com>
Project-URL: source, https://github.com/sami-m-g/lxmlh
Project-URL: homepage, https://github.com/sami-m-g/lxmlh
Project-URL: tracker, https://github.com/sami-m-g/lxmlh/issues
Classifier: Development Status :: 4 - Beta
Classifier: Programming Language :: Python
Classifier: Programming Language :: Python :: 3
Classifier: Programming Language :: Python :: 3.8
Classifier: Programming Language :: Python :: 3.9
Classifier: Programming Language :: Python :: 3.10
Classifier: Programming Language :: Python :: 3.11
Classifier: Programming Language :: Python :: 3.12
Classifier: Natural Language :: English
Classifier: Operating System :: OS Independent
Requires-Python: >=3.8
License-File: LICENSE
Requires-Dist: lxml==4.9.3
Requires-Dist: numpy>=1.23.3
Provides-Extra: testing
Requires-Dist: lxmlh; extra == "testing"
Requires-Dist: pytest; extra == "testing"
Requires-Dist: pytest-cov; extra == "testing"
Requires-Dist: python-coveralls; extra == "testing"
Provides-Extra: dev
Requires-Dist: build; extra == "dev"
Requires-Dist: pre-commit; extra == "dev"
Requires-Dist: pylint; extra == "dev"
Requires-Dist: pytest; extra == "dev"
Requires-Dist: pytest-cov; extra == "dev"
Requires-Dist: pytest-randomly; extra == "dev"
Requires-Dist: setuptools; extra == "dev"
Requires-Dist: sphinx; extra == "dev"
Requires-Dist: sphinx-rtd-theme; extra == "dev"
